zssc/cache.py
zssc-0.1.1.dist-info/licenses/LICENSE
zssc-0.1.1.dist-info/METADATA
zssc-0.1.1.dist-info/WHEEL
zssc-0.1.1.dist-info/top_level.txt
zssc-0.1.1.dist-info/RECORD
