Metadata-Version: 2.4
Name: zssc
Version: 0.1.1
Summary: Personal tools
Requires-Python: >=3.12
License-File: LICENSE
Dynamic: license-file
